pywoc/__init__.py
pywoc/radial_profile.py
pywoc/woc.py
woc/__init__.py
woc/radial.py
woc/radial_profile.py
woc/woc.py
pywoc-0.1.0.dist-info/LICENSE
pywoc-0.1.0.dist-info/METADATA
pywoc-0.1.0.dist-info/WHEEL
pywoc-0.1.0.dist-info/top_level.txt
pywoc-0.1.0.dist-info/RECORD
